pgbase/__init__.py
pgbase/constants.py
pgbase/core.py
pgbase/exceptions.py
pgbase/models.py
pgbase/testing.py
pgbase/types.py
pgbase/utils.py
pgbase-0.0.3.dist-info/LICENSE
pgbase-0.0.3.dist-info/METADATA
pgbase-0.0.3.dist-info/WHEEL
pgbase-0.0.3.dist-info/RECORD
